PyVXML/__init__.py
PyVXML/pyvxml.py
PyVXML-0.2.dist-info/DESCRIPTION.rst
PyVXML-0.2.dist-info/METADATA
PyVXML-0.2.dist-info/RECORD
PyVXML-0.2.dist-info/WHEEL
PyVXML-0.2.dist-info/metadata.json
PyVXML-0.2.dist-info/top_level.txt
