Metadata-Version: 2.0
Name: PyVXML
Version: 0.2
Summary: PyVXML Project for VXML2.0
Home-page: TBA
Author: Amit Anand
Author-email: onewaytoconnect@gmail.com
License: MIT
Keywords: vxml vxml2.0 pyvxml
Platform: UNKNOWN
Classifier: Development Status :: 4 - Beta
Classifier: Intended Audience :: Developers
Classifier: Topic :: Software Development :: Build Tools
Classifier: License :: OSI Approved :: MIT License
Classifier: Programming Language :: Python :: 2
Classifier: Programming Language :: Python :: 2.6
Classifier: Programming Language :: Python :: 2.7
Classifier: Programming Language :: Python :: 3
Classifier: Programming Language :: Python :: 3.2
Classifier: Programming Language :: Python :: 3.3
Classifier: Programming Language :: Python :: 3.4
